dataframeit/__init__.py
dataframeit/core.py
dataframeit/errors.py
dataframeit/llm.py
dataframeit/py.typed
dataframeit/utils.py
dataframeit-0.5.0.dist-info/METADATA
dataframeit-0.5.0.dist-info/WHEEL
dataframeit-0.5.0.dist-info/licenses/LICENSE
dataframeit-0.5.0.dist-info/RECORD
