Metadata-Version: 2.4
Name: dataframeit
Version: 0.5.0
Summary: Enriqueça DataFrames com análises de texto usando LLMs. Extraia informações estruturadas de textos com Pydantic.
Project-URL: Homepage, https://github.com/bdcdo/dataframeit
Project-URL: Documentation, https://github.com/bdcdo/dataframeit#readme
Project-URL: Repository, https://github.com/bdcdo/dataframeit.git
Project-URL: Issues, https://github.com/bdcdo/dataframeit/issues
Project-URL: Changelog, https://github.com/bdcdo/dataframeit/releases
Author: Bruno da Cunha de Oliveira
Maintainer: Bruno da Cunha de Oliveira
License-Expression: MIT
License-File: LICENSE
Keywords: data-enrichment,dataframe,gemini,langchain,llm,nlp,pandas,pydantic,structured-output,text-extraction
Classifier: Development Status :: 4 - Beta
Classifier: Intended Audience :: Developers
Classifier: Intended Audience :: Science/Research
Classifier: License :: OSI Approved :: MIT License
Classifier: Operating System :: OS Independent
Classifier: Programming Language :: Python :: 3
Classifier: Programming Language :: Python :: 3.10
Classifier: Programming Language :: Python :: 3.11
Classifier: Programming Language :: Python :: 3.12
Classifier: Programming Language :: Python :: 3.13
Classifier: Topic :: Scientific/Engineering :: Artificial Intelligence
Classifier: Topic :: Text Processing :: Linguistic
Classifier: Typing :: Typed
Requires-Python: >=3.10
Requires-Dist: langchain-core>=0.3.0
Requires-Dist: langchain>=0.3.0
Requires-Dist: pandas
Requires-Dist: pydantic>=2.0
Requires-Dist: tqdm
Provides-Extra: all
Requires-Dist: langchain-anthropic>=0.3.0; extra == 'all'
Requires-Dist: langchain-google-genai>=2.0.0; extra == 'all'
Requires-Dist: langchain-openai>=0.3.0; extra == 'all'
Requires-Dist: polars>=0.20; extra == 'all'
Provides-Extra: anthropic
Requires-Dist: langchain-anthropic>=0.3.0; extra == 'anthropic'
Provides-Extra: dev
Requires-Dist: pytest-cov>=4.0; extra == 'dev'
Requires-Dist: pytest>=7.0; extra == 'dev'
Requires-Dist: ruff>=0.1.0; extra == 'dev'
Provides-Extra: google
Requires-Dist: langchain-google-genai>=2.0.0; extra == 'google'
Provides-Extra: openai
Requires-Dist: langchain-openai>=0.3.0; extra == 'openai'
Provides-Extra: polars
Requires-Dist: polars>=0.20; extra == 'polars'
